.gitignore
CHANGES.txt
LICENSE.txt
MANIFEST.in
README.rst
setup.cfg
setup.py
tox.ini
pyramid_zope_request/__init__.py
pyramid_zope_request/tests.py
pyramid_zope_request.egg-info/PKG-INFO
pyramid_zope_request.egg-info/SOURCES.txt
pyramid_zope_request.egg-info/dependency_links.txt
pyramid_zope_request.egg-info/entry_points.txt
pyramid_zope_request.egg-info/not-zip-safe
pyramid_zope_request.egg-info/requires.txt
pyramid_zope_request.egg-info/top_level.txt